copynet_tf/__init__.py
copynet_tf/decoder.py
copynet_tf/decoderv2.py
copynet_tf/loss.py
copynet_tf/metrics.py
copynet_tf/types.py
copynet_tf/util.py
copynet_tf/vocab.py
copynet_tf/layers/__init__.py
copynet_tf/layers/additive_attention.py
copynet_tf/layers/fixed_dense.py
copynet_tf/layers/fixed_embedding.py
copynet_tf/search/__init__.py
copynet_tf/search/beam_search.py
copynet_tf/search/greedy_search.py
copynet_tf/search/searcher.py
copynet_tf-0.2.0.dist-info/METADATA
copynet_tf-0.2.0.dist-info/WHEEL
copynet_tf-0.2.0.dist-info/top_level.txt
copynet_tf-0.2.0.dist-info/RECORD
