Metadata-Version: 2.1
Name: copynet-tf
Version: 0.2.0
Summary: CopyNet with TensorFlow 2.0
Home-page: https://github.com/pavanchhatpar/copynet-tf
Author: Pavan Chhatpar
Author-email: pavanchhatpar@gmail.com
License: UNKNOWN
Platform: UNKNOWN
